arrayduplicateoperations/__init__.py
arrayduplicateoperations/arrayduplicateoperations.py
arrayduplicateoperations/test.py
arraydraked-0.0.3.dist-info/METADATA
arraydraked-0.0.3.dist-info/WHEEL
arraydraked-0.0.3.dist-info/top_level.txt
arraydraked-0.0.3.dist-info/RECORD
