Metadata-Version: 2.1
Name: arraydraked
Version: 0.0.3
Summary: An array duplicate checker
Home-page: UNKNOWN
Author: Aswin Sankar
Author-email: <AswinSankar18@outlook.com>
License: UNKNOWN
Keywords: array,duplicate
Platform: UNKNOWN
Classifier: Development Status :: 1 - Planning
Classifier: Intended Audience :: Developers
Classifier: Programming Language :: Python :: 3
Classifier: Operating System :: Unix
Classifier: Operating System :: MacOS :: MacOS X
Classifier: Operating System :: Microsoft :: Windows
